{
  "id": "211d0391-1352-44ca-9851-5b61094b4872",
  "epochs": [],
  "train_loss": [],
  "val_loss": [],
  "rl2_error": [],
  "l2_error": [],
  "wall_time": 0.2243341989815235,
  "it_per_sec": 26.745810613094122,
  "metadata": {
    "n_input_channels": 2,
    "n_output_channels": 1,
    "n_params": 1,
    "hidden_channels": 64,
    "modes1": 16,
    "modes2": 16,
    "num_blocks": [
      1,
      1,
      1,
      1
    ],
    "activation": "gelu",
    "norm": false,
    "lr": 0.001,
    "weight_decay": 0.0,
    "u_mean": null,
    "u_std": null,
    "metrics_out_path": "outputs/eff_convection_fno/metrics.json",
    "plot_out_path": "outputs/eff_convection_fno/gt_pred_abs_error.png",
    "plot_max_rows": 16,
    "_instantiator": "pytorch_lightning.cli.instantiate_module",
    "interp_relative_l2_mean": 0.15561973450239747,
    "interp_relative_l2_std": 0.1960198645886438,
    "interp_relative_l2": 0.15561973450239747,
    "extrap_relative_l2_mean": 0.27577268742024896,
    "extrap_relative_l2_std": 0.18936525323626444,
    "extrap_relative_l2": 0.27577268742024896,
    "test_wall_time_sec": 0.2243341989815235,
    "test_batches_per_sec": 26.745810613094122,
    "test_samples_per_sec": 178.30540408729414,
    "interp_samples_per_sec": 89.15270204364707,
    "extrap_samples_per_sec": 89.15270204364707,
    "test_ms_per_sample": 5.608354974538088,
    "per_solution": {
      "interp": [
        {
          "z": [
            4.332684516906738
          ],
          "rl2": 0.14255470037460327
        },
        {
          "z": [
            3.8786370754241943
          ],
          "rl2": 0.05577434226870537
        },
        {
          "z": [
            23.47315216064453
          ],
          "rl2": 0.017156943678855896
        },
        {
          "z": [
            25.017824172973633
          ],
          "rl2": 0.007819613441824913
        },
        {
          "z": [
            17.365978240966797
          ],
          "rl2": 0.010123154148459435
        },
        {
          "z": [
            12.766318321228027
          ],
          "rl2": 0.07216031849384308
        },
        {
          "z": [
            8.050970077514648
          ],
          "rl2": 0.4120420813560486
        },
        {
          "z": [
            10.230905532836914
          ],
          "rl2": 0.5676766633987427
        },
        {
          "z": [
            13.75616455078125
          ],
          "rl2": 0.028680531308054924
        },
        {
          "z": [
            13.66161060333252
          ],
          "rl2": 0.027235256507992744
        },
        {
          "z": [
            5.051539897918701
          ],
          "rl2": 0.16283440589904785
        },
        {
          "z": [
            22.95362091064453
          ],
          "rl2": 0.07981667667627335
        },
        {
          "z": [
            16.932449340820312
          ],
          "rl2": 0.0470072478055954
        },
        {
          "z": [
            9.0056791305542
          ],
          "rl2": 0.5567927956581116
        },
        {
          "z": [
            9.525720596313477
          ],
          "rl2": 0.5847107172012329
        },
        {
          "z": [
            17.9320068359375
          ],
          "rl2": 0.04694393649697304
        },
        {
          "z": [
            24.915119171142578
          ],
          "rl2": 0.005935853347182274
        },
        {
          "z": [
            4.624011516571045
          ],
          "rl2": 0.16518808901309967
        },
        {
          "z": [
            14.397337913513184
          ],
          "rl2": 0.005441074725240469
        },
        {
          "z": [
            5.714797019958496
          ],
          "rl2": 0.11650028824806213
        }
      ],
      "extrap": [
        {
          "z": [
            28.135988235473633
          ],
          "rl2": 0.15124540030956268
        },
        {
          "z": [
            1.603670358657837
          ],
          "rl2": 0.5696474313735962
        },
        {
          "z": [
            3.2782318592071533
          ],
          "rl2": 0.1301899403333664
        },
        {
          "z": [
            3.3435332775115967
          ],
          "rl2": 0.10820931941270828
        },
        {
          "z": [
            29.280858993530273
          ],
          "rl2": 0.5923840403556824
        },
        {
          "z": [
            3.15641188621521
          ],
          "rl2": 0.17130255699157715
        },
        {
          "z": [
            27.839567184448242
          ],
          "rl2": 0.06413894146680832
        },
        {
          "z": [
            28.113285064697266
          ],
          "rl2": 0.14372864365577698
        },
        {
          "z": [
            1.1375563144683838
          ],
          "rl2": 0.6211629509925842
        },
        {
          "z": [
            3.5503876209259033
          ],
          "rl2": 0.0402127280831337
        },
        {
          "z": [
            3.286766767501831
          ],
          "rl2": 0.12731286883354187
        },
        {
          "z": [
            28.16588020324707
          ],
          "rl2": 0.16133159399032593
        },
        {
          "z": [
            28.777496337890625
          ],
          "rl2": 0.3998531997203827
        },
        {
          "z": [
            28.610532760620117
          ],
          "rl2": 0.3311791718006134
        },
        {
          "z": [
            2.99110746383667
          ],
          "rl2": 0.2264573574066162
        },
        {
          "z": [
            2.940535068511963
          ],
          "rl2": 0.2430281639099121
        },
        {
          "z": [
            27.791044235229492
          ],
          "rl2": 0.05231674015522003
        },
        {
          "z": [
            1.824863314628601
          ],
          "rl2": 0.5330480933189392
        },
        {
          "z": [
            2.3826091289520264
          ],
          "rl2": 0.40859702229499817
        },
        {
          "z": [
            28.875980377197266
          ],
          "rl2": 0.4401075839996338
        }
      ]
    }
  }
}